{"cameraMode":{"drawMode":0,"name":"Shaded","section":"Shading Mode"},"sceneLighting":true,"audioPlay":false,"sceneViewState":{"m_AlwaysRefresh":false,"showFog":true,"showSkybox":true,"showFlares":true,"showImageEffects":true,"showParticleSystems":true,"showVisualEffectGraphs":true,"m_FxEnabled":true},"in2DMode":false,"pivot":{"x":-0.007985591888427735,"y":0.7438451647758484,"z":0.1977090835571289},"rotation":{"x":-0.04757729917764664,"y":0.12939390540122987,"z":-0.0062158419750630859,"w":-0.9904331564903259},"size":1.2247449159622193,"orthographic":false}